Workbook

Sheet Totals
A1: ADMIN | C1: ='2025'!H48 -> 155587 | D1: =(C1/C10) -> 0.089938758
A2: MAINT | C2: ='2025'!H71 -> 232645 | D2: =(C2/C10) -> 0.13448297
A3: OTHER | C3: ='2025'!H87 -> 561810 | D3: =(C3/C10) -> 0.32476038
A4: UTILITIES | C4: ='2025'!H99 -> 423800 | D4: =(C4/C10) -> 0.2449822
A5: RESERVE | C5: ='2025'!H129 -> 256479.6 | D5: =(C5/C10) -> 0.14826082
A6: GROUNDS | C6: ='2025'!H57 -> 99600 | D6: =C6/C10 -> 0.057574864
C10: =SUM(C1:C6) -> 1729921.6 | D10: =SUM(D1:D6) -> 1

Sheet 2025
D1: 2025 BUDGET | F1: 2025 Projected | H1: 2026 BUDGET
D2: (2024 Rolled Over)
B3: Assessment
B4: Per Unit Per Month | D4: 486 | F4: =D4 -> 486 | H4: =H6/12 -> 684.58188
B6: Assessment For Year | D6: 5825.8998 | F6: =D6 -> 5825.8998 | H6: =(H25+H13)/195 -> 8214.9825
B7: ((a+b)/195 units)
B9: INCOME
B11: OPERATING
A13: 5000 | B13: Assessments | D13: 998385 | E13: a | F13: =D13 -> 998385 | H13: =H21-(H14+H16+H17+H18+H19) -> 1345442 | I13: a
B14: Application Fees | D14: 0 | F14: 0 | H14: 0
A15: 5018 | B15: Clubhouse Rental Income | D15: 0 | F15: 1480 | H15: 0
A16: 5010 | B16: Other Income | D16: 500 | F16: 1500 | H16: 0
A17: 5040 | B17: Collection Income | D17: 2250 | F17: 1325 | H17: 0
A18: 1030 | B18: Oper Interest Income | D18: 900 | F18: 4000 | H18: 2000
A19: 5017 | B19: Unit Rental Income | D19: 22800 | F19: 22800 | H19: 26400
B21: TOTAL OPERATING | D21: 1026835 | F21: =F13+F14+F16+F17+F18+F19 -> 1028010 | H21: =H101 -> 1373842
B23: RESERVES
A25: 3000 | B25: Assessments | D25: 137665.47 | E25: b | F25: =D25 -> 137665.47 | H25: =H29-H27-H26 -> 256479.6 | I25: b
A26: 3010 | B26: Interest | D26: 0 | F26: 0 | H26: 0
A27: 5020 | B27: Special Asmnts | D27: 0 | F27: 455325 | H27: 0
B29: TOTAL RESERVES | D29: 137666 | F29: =F25+F26 -> 137665.47 | H29: =H129 -> 256479.6
B32: TOTAL INCOME | D32: 1164500.5 | F32: =F21+F29 -> 1165675.5 | H32: =H21+H29 -> 1630321.6
B35: EXPENSES
B37: ADMINISTRATION
A39: 6040 | B39: Attorney | D39: 8000 | F39: 45000 | H39: 40000
A40: 6030 | B40: Bank Charges | D40: 200 | F40: 500 | H40: 500
A41: 6010 | B41: CPA | D41: 5325 | F41: 5325 | H41: 5500
A42: 6050 | B42: Management Fees | D42: 33930 | F42: 33930 | H42: 35287
A43: 6790 | B43: Labels/Supplies/Misc | D43: 1500 | F43: 500 | H43: 500
A44: 6810a | B44: Payroll - Maintenance | D44: 32500 | F44: 40000 | H44: 39000
A45: 6810b | B45: Payroll - Office | D45: 26000 | F45: 28000 | H45: 31200
A46: 6020 | B46: Postage/Printing | D46: 2200 | F46: 3600 | H46: 3600
B48: TOTAL ADMINISTRATION | D48: 109655 | F48: =SUM(F39:F47) -> 156855 | H48: =SUM(H39:H47) -> 155587
B51: MAINTENANCE
A53: 6230 | B53: Building Repairs | D53: 25000 | F53: 30000 | H53: 25770
A54: 6261 | B54: Rec. Equip | D54: 1200 | F54: 1200 | H54: 1200
B55: Electrical Repair | D55: 0 | F55: 0 | H55: 0
B56: Fire Protection | D56: 0 | F56: 0 | H56: 0
A57: 6140 | B57: Ground Maint. | D57: 101430 | F57: 101430 | H57: 99600
B58: Irrigation System | D58: 0 | F58: 0 | H58: 0
A59: 6240 | B59: Janitorial | D59: 8500 | F59: 8500 | H59: 8000
A60: 6160 | B60: Lake Maintenance | D60: 1400 | F60: 1400 | H60: 600
A61: 6142 | B61: Misc. Landscaping | D61: 2000 | F61: 14000 | H61: 3600
A62: 6144 | B62: Supplies | D62: 500 | F62: 500 | H62: 5000
A63: 6171 | B63: Streetlight Repair | D63: 500 | F63: 100 | H63: 500
A64: 6120 | B64: Pest Control | D64: 10000 | F64: 25000 | H64: 20000
A65: 6200 | B65: Pool Maintenance | D65: 8000 | F65: 7000 | H65: 8375
A66: 6130 | B66: Plumbing | D66: 46000 | F66: 30000 | H66: 46000
A67: 6821 | B67: Social Functions | D67: 2000 | F67: 2000 | H67: 2000
A68: 6143 | B68: Tree Trimming | D68: 13000 | F68: 7000 | H68: 12000
B69: Walkways/Sidewalks | D69: 0 | F69: 0 | H69: 0
B71: TOTAL MAINTENANCE | D71: 219530 | F71: =SUM(F53:F70) -> 228130 | H71: =SUM(H53:H70) -> 232645
B74: OTHER EXPENSES
A76: 6703 | B76: Annual Corporate Report | D76: 62 | F76: 61 | H76: 62
A77: 6730 | B77: Collections/Bad Debt | D77: 200 | F77: 500 | H77: 0
A78: 6700 | B78: Filing & Licenses | D78: 1713 | F78: 1700 | H78: 1700
A79: 6750 | B79: Fees to Division | D79: 800 | F79: 780 | H79: 800
A80: 6710 | B80: Income Taxes | D80: 600 | F80: 2100 | H80: 1000
A81: 6720 | B81: Insurance | D81: 300000 | F81: 523634 | H81: 552723
A82: 6212 | B82: Orientation | D82: 200 | F82: 0 | H82: 400
A83: 6060 | B83: Background Checks | D83: 1000 | F83: 1000 | H83: 1000
A84: 6236 | B84: Rental Unit Expense | D84: 2000 | F84: 2500 | H84: 4000
A85: 6701 | B85: Pool/Spa Permit | D85: 125 | F85: 125 | H85: 125
B87: TOTAL OTHER | D87: 306700 | F87: =SUM(F75:F86) -> 532400 | H87: =SUM(H75:H86) -> 561810
B90: UTILITIES
A92: 6600 | B92: Cable TV | D92: 130000 | F92: 130000 | H92: 107640
A93: 6610 | B93: Electricity | D93: 18000 | F93: 16416 | H93: 18000
A94: 6616 | B94: Electricity - Street Light | D94: 650 | F94: 650 | H94: 650
A95: 6620 | B95: Telephone | D95: 4300 | F95: 4300 | H95: 4300
A96: 6643 | B96: Trash | D96: 62000 | F96: 69618 | H96: 71707
A97: 6640 | B97: Water/Sewer | D97: 176000 | F97: 214013 | H97: 221503
B99: TOTAL UTILITIES | D99: 390950 | F99: =SUM(F91:F97) -> 434997 | H99: =SUM(H91:H97) -> 423800
B101: TOTAL OPERATING | D101: 1026835 | F101: =F48+F71+F87+F99 -> 1352382 | H101: =H48+H71+H87+H99 -> 1373842
B104: RESERVES
A106: 7185 | B106: Clubhouse | D106: 3118.1 | F106: =D106 -> 3118.1 | H106: =Reserve!I5 -> 5392.5287
A107: 7062 | B107: Pool Equipment | D107: 11939.714 | F107: =D107 -> 11939.714 | H107: =Reserve!I7 -> 14932.602
B108: Pool Equipment Special Assessment | D108: 0 | F108: 0 | H108: 0
A109: 6070 | B109: Pool Relining | D109: 0 | F109: 0 | H109: =Reserve!I9 -> 50000
A110: 7015 | B110: Road - Section 1 | D110: 2998.4 | F110: =D110 -> 2998.4 | H110: =Reserve!I11 -> 3267.5013
A111: 7016 | B111: Road - Section 2 | D111: 9588.4286 | F111: =D111 -> 9588.4286 | H111: =Reserve!I13 -> 10965.434
B112: Road- Section 2 Special Assessment | D112: 0 | F112: 0 | H112: 0
A113: 7008 | B113: Painting/Building elements | D113: 16197.875 | F113: =D113 -> 16197.875 | H113: =Reserve!I15 -> 18135.987
A114: 7001 | B114: Common Elements | D114: 478.66667 | F114: =D114 -> 478.66667 | H114: =Reserve!I17 -> 2257.99
A115: 7040 | B115: Plumbing | D115: 11066.889 | F115: =D115 -> 11066.889 | H115: =Reserve!I19 -> 18409.264
A116: 7010 | B116: Roof | D116: 56096.727 | F116: =D116 -> 56096.727 | H116: =Reserve!I21 -> 42243.972
B117: Roof Special Assessment | D117: 0 | F117: 0 | H117: 0
A118: 7012 | B118: Mansard Shingles | D118: 19291.8 | F118: =D118 -> 19291.8 | H118: =Reserve!I23 -> 0
A119: 7210 | B119: Vehicle | D119: 0 | F119: =D119 -> 0 | H119: =Reserve!I25 -> 0.44
A120: 7095 | B120: Lakes | D120: 960.66667 | F120: =D120 -> 960.66667 | H120: =Reserve!I27 -> 1649.83
A121: 7026 | B121: Perimeter | D121: 0 | F121: =D121 -> 0 | H121: =Reserve!I29 -> 630
A122: 7120 | B122: Concrete Drives/Curbs | D122: 2189.2 | F122: =D122 -> 2189.2 | H122: =Reserve!I31 -> 6626.9025
B123: Concrete Drives/Curbs Special Assessment | D123: 0 | F123: 0 | H123: 0
A124: 7160 | B124: Special Projects | D124: 0 | F124: =D124 -> 0 | H124: =Reserve!I33 -> 75000
A125: 7050 | B125: Tree Management | D125: 3739 | F125: =D125 -> 3739 | H125: =Reserve!I35 -> 6967.1433
B126: Tree Management Special Assessment | D126: 0 | F126: 0 | H126: 0
A127: 7005 | B127: Interest | D127: 0 | F127: =D127 -> 0 | H127: =Reserve!I37 -> 0
B129: TOTAL RESERVES | D129: 137665.47 | F129: =SUM(F105:F128) -> 137665.47 | H129: =SUM(H105:H128) -> 256479.6
B131: TOTAL OPERATING/RESERVES | D131: 1164500.5 | F131: =F101+F129 -> 1490047.5 | H131: =H101+H129 -> 1630321.6

Sheet Reserve
B1: Total | C1: Remain | D1: Estimated | E1: Estimated | F1: Balance | G1: Current | I1: Annual
B2: Life | C2: Life | D2: Year | E2: Total Cost | F2: Needed | G2: Balance | I2: Funding
G3: 46023 | I3: 2026
A5: Clubhouse | B5: 15 | C5: 8 | D5: 2034 | E5: 65000 | F5: =(E5-G5) -> 43140.23 | G5: 21859.77 | I5: =F5/(C5) -> 5392.5287
A7: Pool Equipment | B7: 14 | C7: 5 | D7: 2031 | E7: 99700 | F7: =(E7-G7) -> 74663.01 | G7: 25036.99 | I7: =F7/(C7) -> 14932.602
A9: Pool Relining | B9: 15 | C9: 1 | D9: 2026 | E9: 50000 | F9: =E9-G9 -> 50000 | G9: 0 | I9: =F9/(C9) -> 50000
A11: Road - Section 1 | B11: 20 | C11: 8 | D11: 2034 | E11: 62000 | F11: =(E11-G11) -> 26140.01 | G11: 35859.99 | I11: =F11/(C11) -> 3267.5013
A13: Road - Section 2 | B13: 20 | C13: 5 | D13: 2031 | E13: 150000 | F13: =(E13-G13) -> 54827.17 | G13: 95172.83 | I13: =F13/(C13) -> 10965.434
A15: Building | B15: 10 | C15: 6 | D15: 2032 | E15: 185000 | F15: =(E15-G15) -> 108815.92 | G15: 76184.08 | I15: =F15/(C15) -> 18135.987
A17: Common Elements | B17: 10 | C17: 1 | D17: 2030 | E17: 10000 | F17: =(E17-G17) -> 2257.99 | G17: 7742.01 | I17: =F17/(C17) -> 2257.99
A19: Plumbing | B19: 20 | C19: 7 | D19: 2033 | E19: 175000 | F19: =(E19-G19) -> 128864.85 | G19: 46135.15 | I19: =F19/(C19) -> 18409.264
A21: Roof | B21: 15 | C21: 9 | D21: 2035 | E21: 875000 | F21: =(E21-G21) -> 380195.75 | G21: 494804.25 | I21: =F21/(C21) -> 42243.972
A23: Mansard Shingles | B23: 10 | C23: 3 | D23: 2029 | E23: 154615.04 | F23: =(E23-G23) -> 0 | G23: 154615.04 | I23: =F23/(C23) -> 0
A25: Vehicle | B25: 7 | C25: 1 | D25: 2025 | E25: 8812 | F25: =(E25-G25) -> 0.44 | G25: 8811.56 | I25: =F25/(C25) -> 0.44
A27: Lake | B27: 30 | C27: 1 | D27: 2027 | E27: 10000 | F27: =(E27-G27) -> 1649.83 | G27: 8350.17 | I27: =F27/(C27) -> 1649.83
A29: Perimeter | B29: 10 | C29: 1 | D29: 2026 | E29: 630 | F29: =(E29-G29) -> 630 | G29: 0 | I29: =F29/(C29) -> 630
A31: Concrete Drives/Curbs | B31: 20 | C31: 8 | D31: 2034 | E31: 70000 | F31: =(E31-G31) -> 53015.22 | G31: 16984.78 | I31: =F31/(C31) -> 6626.9025
A33: Special Projects/ Termite Remediation | B33: 1 | C33: 1 | D33: 2026 | E33: 75000 | F33: =(E33-G33) -> 75000 | G33: 0 | I33: =F33/(C33) -> 75000
A35: Tree Management | B35: 5 | C35: 3 | D35: 2029 | E35: 25000 | F35: =(E35-G35) -> 20901.43 | G35: 4098.57 | I35: =F35/(C35) -> 6967.1433
A37: Interest | B37: 1 | C37: 1 | D37: 2026 | E37: 8578.07 | F37: =(E37-G37) -> 0 | G37: 8578.07 | I37: =F37/(C37) -> 0
I40: =SUM(I5:I39) -> 256479.6
A42: Formula:
A43: Balance Needed = Estimated Total Cost less Current Balance
A44: Annual Funding = Balance Needed divided by the Remain Life
A46: Many factors can affect future costs. This reserve projection is based on information available
A47: at this time. Information has been obtained from contractors and costs associated with similar
A48: replacements.
