Workbook

Sheet Budget 
F1: 2025 Budget | H1: Projected 2025 | J1: 2026 BUDGET
A2: Member Assessment | F2: 550 | H2: 550 | J2: =J4/12 -> 584.99977
A3: Per Month Per Unit
A4: Assessment For Year | F4: 6600 | H4: =H2*12 -> 6600 | J4: =(J19)/168 -> 7019.9972
A5: ((a+b)/168 units)
A7: REVENUES:
A9: OPERATING
A10: Member Assmts | F10: 927680 | H10: =F10 -> 927680 | J10: =SUM(J76+J69+J57+J30-J11) -> 957069.53
A11: Income/Carport | F11: 2800 | H11: 2800 | J11: 50
A12: TOTAL OPERATING | F12: 930480 | H12: =SUM(H10:H11) -> 930480 | J12: =SUM(J10+J11) -> 957119.53
A14: RESERVES
A15: Reserve Assessment | F15: 181120 | H15: =F15 -> 181120 | J15: =J89-J16 -> 221240 | L15: Reserves went down.. Do we want to increaes.. This is just based on schedule.
A16: Interest | F16: 0 | H16: 1000 | J16: 1000
A17: TOTAL RESERVES | F17: 181120 | H17: =SUM(H15:H16) -> 182120 | J17: =SUM(J15+J16) -> 222240
A19: TOTAL INCOME | F19: 1108800 | H19: =H12+H17 -> 1112600 | J19: =J12+J17 -> 1179359.5
A21: EXPENSES
A23: ADMINISTRATION
A24: CPA Fees | F24: 12000 | H24: 7250 | J24: 7500 | K24: *Decreasaed Audit not requried until 2026 tax Audit
A25: Postage & Printing | F25: 2500 | H25: 2000 | J25: 2500
A26: Bank Charges | F26: 900 | H26: 200 | J26: 900
A27: Attorney Fees | F27: 2000 | H27: 3219 | J27: 3000 | K27: *increase?
A28: Management (C&S) | F28: 19920 | H28: 19920 | J28: 20916 | K28: Increase 5%
A29: misc Ad Expense | F29: 1400 | H29: 676 | J29: 1400
A30: TOTAL ADMIN. | F30: 38720 | H30: =SUM(H24:H29) -> 33265 | J30: =SUM(J24:J29) -> 36216
A32: MAINTENANCE
A33: Misc Repair | F33: 1500 | H33: 244 | J33: 1500
A34: Security Exp | F34: 1000 | H34: 0 | J34: 500
A35: Fire Safety | F35: 1800 | H35: 1044 | J35: 1000
A36: Pest Control | F36: 15000 | H36: 13476 | J36: 15000
A37: Drainage | F37: 1000 | H37: 637 | J37: 1000
A38: Grounds Maint. | F38: 52000 | H38: 48000 | J38: 52000
A39: Landscaping | F39: 7000 | H39: 8800 | J39: 7500
A40: Tree Trimming | F40: 12000 | H40: 0 | J40: 13000 | K40: Increase | P40: Decrease
A41: Grounds on Site | F41: 10000 | H41: 0 | J41: 2000
A42: Mulch | F42: 9000 | H42: 0 | J42: 10000
A43: Fertilizer Tru Green | F43: 7000 | H43: 6724 | J43: 8000
A44: Irrigation Maint | F44: 7000 | H44: 1400 | J44: 7000 | K44: Decrease?? | P44: Decrease
A45: Lake Maint | F45: 3000 | H45: 1560 | J45: 16500
A46: Equipment Repair | F46: 2500 | H46: 1000 | J46: 2500
A47: Walkways/Sidewalks | F47: 1500 | H47: 500 | J47: 1500
A48: Electric Maint | F48: 7000 | H48: 13909 | J48: 10000 | K48: Increase ??
A49: Pool Mtce. Contract | F49: 15000 | H49: 27818 | J49: 15000 | K49: Increase ??
A50: Pool Furniture /Supplies | F50: 3000 | H50: 200 | J50: 3000
A51: Build Repair | F51: 25000 | H51: 30000 | J51: 40080 | K51: Increase??
A52: Roof Repair | F52: 5000 | H52: 2500 | J52: 5000
A53: Janitorial/Maint | F53: 400 | H53: 350 | J53: 1200
A54: Rec Bldg / Cleaning | F54: 500 | H54: 200 | J54: 500
A55: misc | F55: 0 | H55: 0 | J55: 0
A56: Payroll | F56: 91900 | H56: 91000 | J56: 98155.2 | K56: Decrease?? Based on history
A57: TOTAL MAINT. | F57: 279100 | H57: 234848 | J57: =SUM(J33:J56) -> 311935.2
A59: OTHER EXPENSES
A60: Filing & License | F60: 300 | H60: 0 | J60: 300
A61: Income Taxes | F61: 5100 | H61: 5000 | J61: 5100
A62: Insurance | F62: 288066 | H62: 288654 | J62: 268581.33 | K62: Increased, but don't know what it will be this yea
A63: Bad Debts | F63: 0 | H63: 0 | J63: 0
A64: Division Fees | F64: 700 | H64: 1000 | J64: 700
A65: Contingency | F65: 41856 | H65: 41856 | J65: 46797 | K65: Do we leave in for hurricane , emergency repairs? | Q65: 41856
A66: Corp Report | F66: 100 | H66: 62 | J66: 100
A67: Office Supplies | F67: 800 | H67: 750 | J67: 800
A68: Pool Permit | F68: 1000 | H68: 1000 | J68: 1000
A69: TOTAL OTHER | F69: 337922 | H69: 213934 | J69: =SUM(J60:J68) -> 323378.33
A71: UTILITIES
A72: Cable | F72: 121338 | H72: 122958 | J72: 127000 | K72: Increase 5%
A73: Electricity | F73: 18000 | H73: 18100 | J73: 18450
A74: Telephone | F74: 2600 | H74: 2638 | J74: 2860
A75: Water/Sewer/Trash | F75: 130000 | H75: 132414 | J75: 137280
A76: TOTAL UTILITIES | F76: 271938 | H76: 204200 | J76: =SUM(J72:J75) -> 285590
A78: TOTAL OPERATING | F78: 927680 | H78: =H30+H57+H69+H76 -> 686247 | J78: =J30+J57+J69+J76 -> 957119.53
A80: RESERVES
A81: Roofs | F81: 48000 | H81: 60000 | J81: =Reserves!G3 -> 49000
A82: Painting | F82: 2000 | H82: 2000 | J82: =Reserves!G4 -> 3000
A83: Building Repairs | F83: 92300 | H83: 9500 | J83: =Reserves!G5 -> 130740
A84: Paving | F84: 33300 | H84: 35000 | J84: =Reserves!G6 -> 35000
A85: Pool | F85: 4900 | H85: 3852 | J85: =Reserves!G7 -> 4000
A86: Lake Bridge Rpr | F86: 500 | H86: 100 | J86: =Reserves!G8 -> 100
A87: Clubhouse | F87: 0 | H87: 2000 | J87: =Reserves!G9 -> 400
A88: Fencing | F88: 100 | H88: 0 | J88: =Reserves!G10 -> .
A89: TOTAL RESERVES | F89: 181120 | H89: 112452 | J89: =Reserves!G12 -> 222240
A91: TOTAL OPERATING AND | F91: 1108800 | H91: 791934 | J91: =J78+J89 -> 1179359.5
A92: RESERVES
A94: SURPLUS | F94: 0 | H94: 0 | J94: 0

Sheet Reserves
B1: Total Life | C1: Remaining | D1: Estimated Current | E1: Net Additional Reserve | F1: Balance at 12/2025 | G1: 2026 Required
B2: In Years | C2: Life In Years | D2: Replacement Cost | E2: Fund Requirements | G2: Reserve Deposits
A3: Roofs | B3: 25 | C3: 7 | D3: 600000 | E3: =(D3-F3) -> 371949 | F3: 228051 | G3: 49000
A4: Paint Bldgs | B4: 10 | C4: 2 | D4: 177500 | E4: =(D4-F4) -> 16466 | F4: 161034 | G4: 3000
A5: Building Repairs | B5: 10 | C5: 1 | D5: 92000 | E5: =(D5-F5) -> 62000 | F5: 30000 | G5: 130740 | I5: Should we increase building reserves Replacment cost… I don’t think we will have much left
A6: Total Paving | B6: 18 | C6: 14 | D6: 145000 | E6: =(D6-F6) -> 70000 | F6: 75000 | G6: 35000 | I6: Took out paving proposal for 2025 $80,000
A7: Total Pool | B7: 15 | C7: 1 | D7: 90000 | E7: =(D7-F7) -> 2828 | F7: 87172 | G7: 4000
A8: Bridge | B8: 45 | C8: 6 | D8: 11600 | E8: =(D8-F8) -> 2110 | F8: 9490 | G8: 100
A9: Fence | B9: 17 | C9: 1 | D9: 3467 | E9: 0 | F9: 2420 | G9: 400
A10: Clubhouse | B10: 20 | C10: 4 | D10: 10000 | E10: 10000 | F10: 2091 | G10: .
A12: Total Reserves | D12: =SUM(D3:D10) -> 1129567 | E12: =SUM(E3:E9) -> 525353 | G12: =SUM(G3:G10) -> 222240
B17: Please refer to the attached schedule per the Boards Spreadsheet
B19: Formula:
B20: Balance Needed = Estimated Total Cost less Current Balance
B21: Annual Funding = Balance Needed divided by the Remain Life (plus current year)
B23: Many factors can affect future costs. This reserve projection is based on information available
B24: at this time. Information has been obtained from contractors and costs associated with similar
B25: replacements.
H44: 5400
H45: 800
